flexible_forms/__init__.py
flexible_forms/admin.py
flexible_forms/apps.py
flexible_forms/cache.py
flexible_forms/fields.py
flexible_forms/forms.py
flexible_forms/models.py
flexible_forms/signals.py
flexible_forms/static/flexible_forms/admin/code-editor-admin-widget.css
flexible_forms/urls.py
flexible_forms/utils.py
flexible_forms/views.py
flexible_forms/widgets.py
django_flexible_forms-0.16.12.dist-info/WHEEL
django_flexible_forms-0.16.12.dist-info/METADATA
django_flexible_forms-0.16.12.dist-info/RECORD
