Metadata-Version: 2.1
Name: django-flexible-forms
Version: 0.16.12
Summary: A reusable Django app for managing database-backed forms.
License: MIT
Author: Eric Abruzzese
Author-email: eric.abruzzese@gmail.com
Requires-Python: >=3.6.2,<4.0.0
Classifier: License :: OSI Approved :: MIT License
Classifier: Programming Language :: Python :: 3
Classifier: Programming Language :: Python :: 3.7
Classifier: Programming Language :: Python :: 3.8
Classifier: Programming Language :: Python :: 3.9
Requires-Dist: django (>=2.2)
Requires-Dist: importlib-metadata; python_version < "3.8"
Requires-Dist: jmespath (>=0.10.0,<0.11.0)
Requires-Dist: requests (>=2.24.0,<3.0.0)
Requires-Dist: simpleeval (>=0.9.10,<0.10.0)
